rkclient/__init__.py
rkclient/admin.py
rkclient/auth.py
rkclient/client.py
rkclient/entities.py
rkclient/factory.py
rkclient/query.py
rkclient/request.py
rkclient/serialization.py
RecordKeeper_Client-3.5.0.dist-info/LICENSE
RecordKeeper_Client-3.5.0.dist-info/METADATA
RecordKeeper_Client-3.5.0.dist-info/WHEEL
RecordKeeper_Client-3.5.0.dist-info/top_level.txt
RecordKeeper_Client-3.5.0.dist-info/RECORD
