Metadata-Version: 2.1
Name: RecordKeeper-Client
Version: 3.5.0
Summary: Client library for accessing Record Keepers Receiver
Home-page: UNKNOWN
Author: ERST
Author-email: noreply@example.ecom
License: GPLv3+
Platform: UNKNOWN
Classifier: Programming Language :: Python :: 3
Classifier: Operating System :: OS Independent
Classifier: License :: OSI Approved :: GNU General Public License v3 or later (GPLv3+)
Classifier: Development Status :: 3 - Alpha
Classifier: Intended Audience :: Information Technology
Requires-Python: >=3.8.0
